{
  "hash": "314b65d7d40486ce35f8cb89bd1a3a4c",
  "result": {
    "markdown": "---\ntitle: '\"Where is the ... key?\"'\nknitr: \n  opts_chunk: \n    echo: false\n    message: false\n    warning: false\n    crop: true\n---\n\n::: {.cell}\n\n:::\n\n\n## Single Quotes vs Backticks\n\nIt's important to distinguish between single quotes: `'` and backticks <code>\\`</code>. They look similar, but aren't interchangeable.\n\nThe backtick key is highlighted in the images of the keyboards below, in the top left side.\n\n::: panel-tabset\n## PC\n\n\n::: {.cell}\n::: {.cell-output-display}\n![](01_keyboarding_files/figure-html/unnamed-chunk-2-1.png){width=960}\n:::\n:::\n\n\n## Mac\n\n\n::: {.cell}\n::: {.cell-output-display}\n![](01_keyboarding_files/figure-html/unnamed-chunk-3-1.png){width=960}\n:::\n:::\n\n:::\n\n## Slash (`/`) vs backslash (`\\`).\n\nThese different symbols will do different things, and aren't interchangeable!\n\n### Slash (`/`) location\n\n::: panel-tabset\n## PC\n\n\n::: {.cell}\n::: {.cell-output-display}\n![](01_keyboarding_files/figure-html/unnamed-chunk-4-1.png){width=960}\n:::\n:::\n\n\n## Mac\n\n\n::: {.cell}\n::: {.cell-output-display}\n![](01_keyboarding_files/figure-html/unnamed-chunk-5-1.png){width=960}\n:::\n:::\n\n:::\n\n### Backslash (`\\`) location\n\n::: panel-tabset\n## PC\n\n\n::: {.cell}\n::: {.cell-output-display}\n![](01_keyboarding_files/figure-html/unnamed-chunk-6-1.png){width=960}\n:::\n:::\n\n\n## Mac\n\n\n::: {.cell}\n::: {.cell-output-display}\n![](01_keyboarding_files/figure-html/unnamed-chunk-7-1.png){width=960}\n:::\n:::\n\n:::\n\n## The tilde `~` key.\n\nTo type the tilde[^1] key you have to hold {{< kbd Shift+` >}}.\n\n[^1]: Pronunciations include \\[tɪl.də\\] and \\[tɪl.di\\]\n\n::: panel-tabset\n## PC\n\n\n::: {.cell}\n::: {.cell-output-display}\n![](01_keyboarding_files/figure-html/unnamed-chunk-8-1.png){width=960}\n:::\n:::\n\n\n## Mac\n\n\n::: {.cell}\n::: {.cell-output-display}\n![](01_keyboarding_files/figure-html/unnamed-chunk-9-1.png){width=960}\n:::\n:::\n\n:::\n\n## The caret `^`\n\nYou can get the caret symbol with {{< kbd Shift+6 >}}\n\n::: panel-tabset\n## PC\n\n\n::: {.cell}\n::: {.cell-output-display}\n![](01_keyboarding_files/figure-html/unnamed-chunk-10-1.png){width=960}\n:::\n:::\n\n\n## Mac\n\n\n::: {.cell}\n::: {.cell-output-display}\n![](01_keyboarding_files/figure-html/unnamed-chunk-11-1.png){width=960}\n:::\n:::\n\n:::\n\n## The Pipe `|`\n\nYou can get the pipe, or vertical bar, with {{< kbd Shift+\\\\ >}}.\n\n::: panel-tabset\n## PC\n\n\n::: {.cell}\n::: {.cell-output-display}\n![](01_keyboarding_files/figure-html/unnamed-chunk-12-1.png){width=960}\n:::\n:::\n\n\n## Mac\n\n\n::: {.cell}\n::: {.cell-output-display}\n![](01_keyboarding_files/figure-html/unnamed-chunk-13-1.png){width=960}\n:::\n:::\n\n:::\n\n## Side Note: \"Smart Quotes\"\n\nIf, at some point, you copy-paste text from the internet into your code or a text file, you might wind up with \"smart quotes\" that make things work weird!\n\n| Regular Quotes | Smart Quotes |\n|----------------|--------------|\n| `\"regular\"`    | `“smart”`      |\n| `'regular'`    | `‘smart’`   |\n\nBe careful not to have smart quotes cropping up in your code or data!\n",
    "supporting": [
      "01_keyboarding_files"
    ],
    "filters": [
      "rmarkdown/pagebreak.lua"
    ],
    "includes": {},
    "engineDependencies": {},
    "preserve": {},
    "postProcess": true
  }
}